django_fakeuser/__init__.py
django_fakeuser-0.0.1.dist-info/METADATA
django_fakeuser-0.0.1.dist-info/WHEEL
django_fakeuser-0.0.1.dist-info/top_level.txt
django_fakeuser-0.0.1.dist-info/RECORD
