Metadata-Version: 2.1
Name: django-fakeuser
Version: 0.0.1
Summary: A simple package named django_fakeuser
Home-page: https://github.com/artifact/django_fakeuser.git
Author: artifact
Author-email: artifact@example.com
License: UNKNOWN
Platform: UNKNOWN
Classifier: Programming Language :: Python :: 3
Classifier: License :: OSI Approved :: MIT License
Classifier: Operating System :: OS Independent
